distllm/__init__.py
distllm/cli.py
distllm/distributed_embedding.py
distllm/distributed_generation.py
distllm/distributed_tokenization.py
distllm/parsl.py
distllm/py.typed
distllm/registry.py
distllm/timer.py
distllm/utils.py
distllm/embed/__init__.py
distllm/embed/datasets/__init__.py
distllm/embed/datasets/base.py
distllm/embed/datasets/fasta.py
distllm/embed/datasets/huggingface.py
distllm/embed/datasets/jsonl.py
distllm/embed/datasets/jsonl_chunk.py
distllm/embed/datasets/single_line.py
distllm/embed/datasets/utils.py
distllm/embed/embedders/__init__.py
distllm/embed/embedders/base.py
distllm/embed/embedders/full_sequence.py
distllm/embed/embedders/semantic_chunk.py
distllm/embed/encoders/__init__.py
distllm/embed/encoders/auto.py
distllm/embed/encoders/base.py
distllm/embed/encoders/esm2.py
distllm/embed/encoders/esmc.py
distllm/embed/poolers/__init__.py
distllm/embed/poolers/base.py
distllm/embed/poolers/last_token.py
distllm/embed/poolers/mean.py
distllm/embed/writers/__init__.py
distllm/embed/writers/base.py
distllm/embed/writers/huggingface.py
distllm/embed/writers/numpy.py
distllm/generate/__init__.py
distllm/generate/generators/__init__.py
distllm/generate/generators/base.py
distllm/generate/generators/huggingface_backend.py
distllm/generate/generators/langchain_backend.py
distllm/generate/generators/vllm_backend.py
distllm/generate/prompts/__init__.py
distllm/generate/prompts/amp_question.py
distllm/generate/prompts/base.py
distllm/generate/prompts/identity.py
distllm/generate/prompts/keyword_selection.py
distllm/generate/prompts/question_answer.py
distllm/generate/prompts/question_chunk.py
distllm/generate/readers/__init__.py
distllm/generate/readers/amp_json.py
distllm/generate/readers/base.py
distllm/generate/readers/huggingface.py
distllm/generate/readers/jsonl.py
distllm/generate/writers/__init__.py
distllm/generate/writers/amp_json.py
distllm/generate/writers/base.py
distllm/generate/writers/huggingface.py
distllm/rag/__init__.py
distllm-1.0.2.dist-info/LICENSE
distllm-1.0.2.dist-info/METADATA
distllm-1.0.2.dist-info/WHEEL
distllm-1.0.2.dist-info/entry_points.txt
distllm-1.0.2.dist-info/top_level.txt
distllm-1.0.2.dist-info/RECORD
