Metadata-Version: 2.2
Name: distllm
Version: 1.0.2
Summary: Distributed Inference for Large Language Models.
Author-email: Alexander Brace <abrace@anl.gov>, Ozan Gokdemir <ogokdemir@uchicago.edu>
License: MIT
Project-URL: homepage, https://github.com/ramanathanlab/distllm
Project-URL: documentation, https://github.com/ramanathanlab/distllm
Project-URL: repository, https://github.com/ramanathanlab/distllm
Classifier: License :: OSI Approved :: MIT License
Classifier: Programming Language :: Python :: 3
Requires-Python: >=3.8
License-File: LICENSE
Requires-Dist: transformers>=4.38.2
Requires-Dist: datasets>=2.18.0
Requires-Dist: bitsandbytes>=0.42.0
Requires-Dist: langchain>=0.2.5
Requires-Dist: langchain-anthropic>=0.1.7
Requires-Dist: langchain-google-genai>=1.0.1
Requires-Dist: accelerate>=0.28.0
Requires-Dist: parsl>=2024.1.29
Requires-Dist: pydantic>=2.6.0
Requires-Dist: typer[all]>=0.9.0
Requires-Dist: nltk>=3.9
Requires-Dist: python-dotenv>=1.0.1
Requires-Dist: peft>=0.10.0
Requires-Dist: sentence-transformers>=3.3.1
Requires-Dist: torch
Provides-Extra: dev
Requires-Dist: covdefaults>=2.2; extra == "dev"
Requires-Dist: coverage; extra == "dev"
Requires-Dist: mypy; extra == "dev"
Requires-Dist: pre-commit; extra == "dev"
Requires-Dist: pytest; extra == "dev"
Requires-Dist: pytest-cov; extra == "dev"
Requires-Dist: ruff; extra == "dev"
Requires-Dist: tox; extra == "dev"
Requires-Dist: virtualenv; extra == "dev"
Requires-Dist: types-PyYAML; extra == "dev"
Requires-Dist: build; extra == "dev"
Requires-Dist: twine; extra == "dev"
Provides-Extra: docs
Requires-Dist: black; extra == "docs"
Requires-Dist: mkdocs-gen-files; extra == "docs"
Requires-Dist: mkdocs-literate-nav; extra == "docs"
Requires-Dist: mkdocs-material==9.4.7; extra == "docs"
Requires-Dist: mkdocs-section-index; extra == "docs"
Requires-Dist: mkdocstrings==0.23.0; extra == "docs"
Requires-Dist: mkdocstrings-python==1.8.0; extra == "docs"
Requires-Dist: mike; extra == "docs"
